README.md
setup.cfg
setup.py
idlewild/__init__.py
idlewild/builder.py
idlewild/parser.py
idlewild/schematools.py
idlewild.egg-info/PKG-INFO
idlewild.egg-info/SOURCES.txt
idlewild.egg-info/dependency_links.txt
idlewild.egg-info/requires.txt
idlewild.egg-info/top_level.txt